{
  "_stub": true,
  "_stubNote": "Minimal stub used when no real catalog is available (fork PRs, Dependabot PRs, anyone without CATALOG_FETCH_TOKEN). Tests that assert on real catalog content (B12/folate slots, EMF mitigation copy, vendor URL routing) detect this marker and skip — see tests/test-dna-recommendations.js and tests/test-emf.js. If you're forking and filling in a real catalog, drop this _stub key once you have content for the slots your tests cover.",
  "region": "INTL",
  "countries": ["worldwide"],
  "slots": {
    "vitamins.vitaminD": {
      "label": "Vitamin D",
      "forms": ["vitamin D3 (cholecalciferol)"],
      "freeActions": [
        "10–20 minutes of midday sun, skin exposure on arms/legs"
      ],
      "foodForms": ["fatty fish (salmon, mackerel)", "egg yolks", "cod liver oil"],
      "card": "Light & Circadian"
    },
    "_internal.emfMeters": {
      "label": "EMF meters",
      "_internal": true
    },
    "_internal.lightDevices": {
      "label": "Light therapy devices",
      "_internal": true
    },
    "env.shieldingPaint": {
      "label": "RF shielding paint",
      "card": "Environment",
      "_emfMitigationTag": "shielding paint (Yshield)"
    }
  },
  "shops": [],
  "vendors": {
    "example": {
      "name": "Example Vendor",
      "homepage": "https://example.com?ref=getbased",
      "coupon": { "code": "EXAMPLE10", "userDiscount": "10%" },
      "regions": ["INTL"]
    }
  },
  "products": {
    "vitamins.vitaminD": [
      {
        "type": "supplement",
        "form": "D3 softgel",
        "brand": "Example Brand",
        "name": "Vitamin D3 5000 IU",
        "url": "https://example.com/vitamin-d3?ref=getbased",
        "affiliateUrl": "https://example.com/vitamin-d3?ref=getbased",
        "regions": ["INTL"],
        "vendorKey": "example"
      }
    ],
    "_internal.emfMeters": [
      {
        "type": "product",
        "key": "example-meter",
        "name": "Example RF Meter",
        "vendor": "Example Vendor",
        "vendorKey": "example",
        "kind": "RF / microwave meter",
        "blurb": "An example product entry. Replace with your own catalog.",
        "url": "https://example.com/rf-meter?ref=getbased",
        "affiliateUrl": "https://example.com/rf-meter?ref=getbased",
        "matchTypes": ["rfMicrowave"],
        "regions": ["INTL"]
      }
    ],
    "_internal.lightDevices": [
      {
        "type": "product",
        "key": "example-panel",
        "name": "Example Light Panel",
        "vendor": "Example Vendor",
        "vendorKey": "example",
        "kind": "Red + near-IR therapy panel",
        "blurb": "Sample light-device catalog entry. The `key` field must match the preset's `catalogSlug` in data/light-device-presets.json so device cards on the Light page can resolve and surface the affiliate link.",
        "url": "https://example.com/light-panel?ref=getbased",
        "affiliateUrl": "https://example.com/light-panel?ref=getbased",
        "regions": ["INTL"]
      }
    ],
    "env.shieldingPaint": [
      {
        "type": "product",
        "name": "Example Shielding Paint",
        "vendor": "Example Vendor",
        "vendorKey": "example",
        "blurb": "Example mitigation product entry.",
        "url": "https://example.com/shielding-paint?ref=getbased",
        "affiliateUrl": "https://example.com/shielding-paint?ref=getbased",
        "regions": ["INTL"]
      }
    ]
  }
}
